stringtopy/__init__.py
stringtopy/_version.py
stringtopy-0.4.dist-info/LICENSE.txt
stringtopy-0.4.dist-info/METADATA
stringtopy-0.4.dist-info/WHEEL
stringtopy-0.4.dist-info/top_level.txt
stringtopy-0.4.dist-info/RECORD
