Metadata-Version: 2.1
Name: stringtopy
Version: 0.4
Summary: stringtopy is a small library to convert strings to a specified type (e.g. int, float or bool), allowing more human friendly input similar to configparser.
Home-page: http://stringtopy.rtfd.io
Author: James Tocknell
Author-email: aragilar@gmail.com
License: 3-clause BSD
Keywords: strings
Platform: UNKNOWN
Classifier: Development Status :: 3 - Alpha
Classifier: Intended Audience :: Developers
Classifier: License :: OSI Approved :: BSD License
Classifier: Programming Language :: Python :: 3
Classifier: Programming Language :: Python :: 3.7
Classifier: Programming Language :: Python :: 3.8
Classifier: Programming Language :: Python :: 3.9
